covid_vision/__init__.py
covid_vision/cli.py
covid_vision/covid_vision.py
covid_vision/data_loader/__init__.py
covid_vision/data_loader/data_loader.py
covid_vision/ml/__init__.py
covid_vision/ml/models/__init__.py
covid_vision/ml/models/abstract_classifier.py
covid_vision/ml/models/covid_cxr.py
covid_vision/preprocess/__init__.py
covid_vision/preprocess/preprocess.py
covid_vision/utils/__init__.py
covid_vision/utils/file_manipulation.py
covid_vision-0.1.4.dist-info/AUTHORS.rst
covid_vision-0.1.4.dist-info/LICENSE
covid_vision-0.1.4.dist-info/METADATA
covid_vision-0.1.4.dist-info/WHEEL
covid_vision-0.1.4.dist-info/entry_points.txt
covid_vision-0.1.4.dist-info/top_level.txt
covid_vision-0.1.4.dist-info/RECORD
