Metadata-Version: 2.1
Name: covid-vision
Version: 0.1.4
Summary: This project aims to develop Computer Vision algorithms to help the detection of COVID-19 virus on images.
Home-page: https://github.com/MRB-Computer-Vision/covid_vision
Author: Edson Cavalcanti Neto
Author-email: profedsoncavalcanti@gmail.com
License: MIT license
Keywords: covid_vision
Platform: UNKNOWN
Classifier: Development Status :: 2 - Pre-Alpha
Classifier: Intended Audience :: Developers
Classifier: License :: OSI Approved :: MIT License
Classifier: Natural Language :: English
Classifier: Programming Language :: Python :: 3
Classifier: Programming Language :: Python :: 3.5
Classifier: Programming Language :: Python :: 3.6
Classifier: Programming Language :: Python :: 3.7
Classifier: Programming Language :: Python :: 3.8
Requires-Python: >=3.5
Requires-Dist: pip (==19.2.3)
Requires-Dist: bump2version (==0.5.11)
Requires-Dist: wheel (==0.33.6)
Requires-Dist: watchdog (==0.9.0)
Requires-Dist: flake8 (==3.7.8)
Requires-Dist: tox (==3.14.0)
Requires-Dist: coverage (==4.5.4)
Requires-Dist: Sphinx (==1.8.5)
Requires-Dist: twine (==1.14.0)
Requires-Dist: pytest (==4.6.5)
Requires-Dist: pytest-runner (==5.1)
Requires-Dist: googledrivedownloader (==0.4)
Requires-Dist: opencv-python (==4.2.0.34)
Requires-Dist: tensorflow (==2.2.0)
Requires-Dist: Keras (==2.3.1)
Requires-Dist: Pillow (==7.1.2)
